.gitignore
CHANGES.txt
INSTALL.txt
README.txt
bootstrap.py
buildout.cfg
setup.py
src/sterch/__init__.py
src/sterch.logfile.egg-info/PKG-INFO
src/sterch.logfile.egg-info/SOURCES.txt
src/sterch.logfile.egg-info/dependency_links.txt
src/sterch.logfile.egg-info/namespace_packages.txt
src/sterch.logfile.egg-info/requires.txt
src/sterch.logfile.egg-info/top_level.txt
src/sterch/logfile/README.txt
src/sterch/logfile/__init__.py
src/sterch/logfile/configure.zcml
src/sterch/logfile/interfaces.py
src/sterch/logfile/log.py
src/sterch/logfile/meta.zcml
src/sterch/logfile/metaconfigure.py
src/sterch/logfile/metadirectives.py
src/sterch/logfile/tests/__init__.py
src/sterch/logfile/tests/test_log_directive.py