Metadata-Version: 1.0
Name: sterch.logfile
Version: 0.1.1
Summary: Provides interfaces, classes and ZCML directives for file logging
Home-page: http://pypi.sterch.net/sterch.logfile
Author: Maksym Polscha
Author-email: maxp@sterch.net
License: ZPL 2.1
Platform: UNKNOWN
Classifier: Development Status :: 5 - Production/Stable
Classifier: Intended Audience :: Developers
Classifier: License :: OSI Approved :: Zope Public License
Classifier: Operating System :: OS Independent
Classifier: Programming Language :: Python :: 2.5
Classifier: Programming Language :: Python :: 2.6
Classifier: Topic :: Software Development :: Libraries :: Python Modules
